kafka_bundle/__init__.py
kafka_bundle/bundle.py
kafka_bundle-2.0.3.dist-info/LICENSE
kafka_bundle-2.0.3.dist-info/WHEEL
kafka_bundle-2.0.3.dist-info/METADATA
kafka_bundle-2.0.3.dist-info/RECORD
