Metadata-Version: 2.1
Name: kafka-bundle
Version: 2.0.3
Summary: 
Author: Alvaro Garcia
Author-email: maxpowel@gmail.com
Requires-Python: >=3.6,<4.0
Classifier: Programming Language :: Python :: 3
Classifier: Programming Language :: Python :: 3.6
Classifier: Programming Language :: Python :: 3.7
Classifier: Programming Language :: Python :: 3.8
Classifier: Programming Language :: Python :: 3.9
Requires-Dist: applauncher (>=2.0.0,<3.0.0)
Requires-Dist: confluent-kafka (>=1.6.1,<2.0.0)
